aliyunsdkpush/__init__.py
aliyunsdkpush/endpoint.py
aliyunsdkpush/request/__init__.py
aliyunsdkpush/request/v20160801/BindAliasRequest.py
aliyunsdkpush/request/v20160801/BindPhoneRequest.py
aliyunsdkpush/request/v20160801/BindTagRequest.py
aliyunsdkpush/request/v20160801/CancelPushRequest.py
aliyunsdkpush/request/v20160801/CheckCertificateRequest.py
aliyunsdkpush/request/v20160801/CheckDeviceRequest.py
aliyunsdkpush/request/v20160801/CheckDevicesRequest.py
aliyunsdkpush/request/v20160801/CompleteContinuouslyPushRequest.py
aliyunsdkpush/request/v20160801/ContinuouslyPushRequest.py
aliyunsdkpush/request/v20160801/ListSummaryAppsRequest.py
aliyunsdkpush/request/v20160801/ListTagsRequest.py
aliyunsdkpush/request/v20160801/MassPushRequest.py
aliyunsdkpush/request/v20160801/PushMessageToAndroidRequest.py
aliyunsdkpush/request/v20160801/PushMessageToiOSRequest.py
aliyunsdkpush/request/v20160801/PushNoticeToAndroidRequest.py
aliyunsdkpush/request/v20160801/PushNoticeToiOSRequest.py
aliyunsdkpush/request/v20160801/PushRequest.py
aliyunsdkpush/request/v20160801/QueryAliasesRequest.py
aliyunsdkpush/request/v20160801/QueryDeviceInfoRequest.py
aliyunsdkpush/request/v20160801/QueryDeviceStatRequest.py
aliyunsdkpush/request/v20160801/QueryDevicesByAccountRequest.py
aliyunsdkpush/request/v20160801/QueryDevicesByAliasRequest.py
aliyunsdkpush/request/v20160801/QueryPushRecordsRequest.py
aliyunsdkpush/request/v20160801/QueryPushStatByAppRequest.py
aliyunsdkpush/request/v20160801/QueryPushStatByMsgRequest.py
aliyunsdkpush/request/v20160801/QueryTagsRequest.py
aliyunsdkpush/request/v20160801/QueryUniqueDeviceStatRequest.py
aliyunsdkpush/request/v20160801/RemoveTagRequest.py
aliyunsdkpush/request/v20160801/UnbindAliasRequest.py
aliyunsdkpush/request/v20160801/UnbindPhoneRequest.py
aliyunsdkpush/request/v20160801/UnbindTagRequest.py
aliyunsdkpush/request/v20160801/__init__.py
aliyun_python_sdk_push-3.13.21.dist-info/LICENSE
aliyun_python_sdk_push-3.13.21.dist-info/METADATA
aliyun_python_sdk_push-3.13.21.dist-info/WHEEL
aliyun_python_sdk_push-3.13.21.dist-info/top_level.txt
aliyun_python_sdk_push-3.13.21.dist-info/RECORD
